pytidbrep
